pynm/__init__.py
pynm/cli.py
pynm/pynm.py
pynm/util.py
pynm/models/__init__.py
pynm/models/approx.py
pynm/models/centiles.py
pynm/models/gamlss.py
pynm/models/loess.py
test/__init__.py
test/test_pynm.py
pynm-1.0.0.dist-info/LICENSE
pynm-1.0.0.dist-info/METADATA
pynm-1.0.0.dist-info/WHEEL
pynm-1.0.0.dist-info/entry_points.txt
pynm-1.0.0.dist-info/top_level.txt
pynm-1.0.0.dist-info/RECORD
